yupy/__init__.py
yupy/array_schema.py
yupy/icomparable_schema.py
yupy/ischema.py
yupy/isized_schema.py
yupy/locale.py
yupy/mapping_schema.py
yupy/mixed_schema.py
yupy/number_schema.py
yupy/schema.py
yupy/string_schema.py
yupy/validation_error.py
yupy/util/__init__.py
yupy/util/concat_path.py
yupy/util/types.py
yupy-0.1.8.dist-info/licenses/LICENSE
yupy-0.1.8.dist-info/METADATA
yupy-0.1.8.dist-info/WHEEL
yupy-0.1.8.dist-info/top_level.txt
yupy-0.1.8.dist-info/RECORD
