Metadata-Version: 2.4
Name: yupy
Version: 0.1.8
Summary: Dead simple Object schema validation for python
Author: o-murphy
License: The MIT License (MIT)
Project-URL: Homepage, https://github.com/o-murphy/yup
Project-URL: Bug Reports, https://github.com/o-murphy/yup/issues
Project-URL: Source, https://github.com/o-murphy/yup
Keywords: yup,json,python,python3,validator,schema-validator
Classifier: Intended Audience :: Developers
Classifier: Natural Language :: English
Classifier: Programming Language :: Python
Classifier: Topic :: Software Development :: Libraries :: Python Modules
Classifier: Programming Language :: Python :: 3
Classifier: Programming Language :: Python :: 3 :: Only
Classifier: Programming Language :: Python :: 3.9
Classifier: Programming Language :: Python :: 3.10
Classifier: Programming Language :: Python :: 3.11
Classifier: Programming Language :: Python :: 3.12
Classifier: Programming Language :: Python :: Implementation :: CPython
Requires-Python: >=3.10
License-File: LICENSE
Requires-Dist: typing-extensions>=4.13.2
Dynamic: license-file
